jx_sqlite/__init__.py
jx_sqlite/edges.py
jx_sqlite/format.py
jx_sqlite/group.py
jx_sqlite/insert.py
jx_sqlite/meta_columns.py
jx_sqlite/query.py
jx_sqlite/setop.py
jx_sqlite/utils.py
jx_sqlite/window.py
jx_sqlite/expressions/__init__.py
jx_sqlite/expressions/_utils.py
jx_sqlite/expressions/abs_op.py
jx_sqlite/expressions/add_op.py
jx_sqlite/expressions/aggregate_op.py
jx_sqlite/expressions/and_op.py
jx_sqlite/expressions/between_op.py
jx_sqlite/expressions/case_op.py
jx_sqlite/expressions/coalesce_op.py
jx_sqlite/expressions/concat_op.py
jx_sqlite/expressions/count_op.py
jx_sqlite/expressions/date_op.py
jx_sqlite/expressions/default_op.py
jx_sqlite/expressions/div_op.py
jx_sqlite/expressions/eq_op.py
jx_sqlite/expressions/exists_op.py
jx_sqlite/expressions/exp_op.py
jx_sqlite/expressions/filter_op.py
jx_sqlite/expressions/find_op.py
jx_sqlite/expressions/first_op.py
jx_sqlite/expressions/floor_op.py
jx_sqlite/expressions/format_op.py
jx_sqlite/expressions/from_unix_op.py
jx_sqlite/expressions/get_op.py
jx_sqlite/expressions/gt_op.py
jx_sqlite/expressions/gte_op.py
jx_sqlite/expressions/in_op.py
jx_sqlite/expressions/is_boolean_op.py
jx_sqlite/expressions/is_integer_op.py
jx_sqlite/expressions/is_number_op.py
jx_sqlite/expressions/is_text_op.py
jx_sqlite/expressions/last_op.py
jx_sqlite/expressions/least_op.py
jx_sqlite/expressions/leaves_op.py
jx_sqlite/expressions/left_op.py
jx_sqlite/expressions/length_op.py
jx_sqlite/expressions/limit_op.py
jx_sqlite/expressions/literal.py
jx_sqlite/expressions/lt_op.py
jx_sqlite/expressions/lte_op.py
jx_sqlite/expressions/max_op.py
jx_sqlite/expressions/min_op.py
jx_sqlite/expressions/missing_op.py
jx_sqlite/expressions/most_op.py
jx_sqlite/expressions/mul_op.py
jx_sqlite/expressions/ne_op.py
jx_sqlite/expressions/nested_op.py
jx_sqlite/expressions/not_left_op.py
jx_sqlite/expressions/not_op.py
jx_sqlite/expressions/not_right_op.py
jx_sqlite/expressions/offset_op.py
jx_sqlite/expressions/or_op.py
jx_sqlite-5.673.25037.dist-info/LICENSE
jx_sqlite-5.673.25037.dist-info/METADATA
jx_sqlite-5.673.25037.dist-info/WHEEL
jx_sqlite-5.673.25037.dist-info/top_level.txt
jx_sqlite-5.673.25037.dist-info/RECORD
