Metadata-Version: 2.2
Name: jx-sqlite
Version: 5.673.25037
Summary: JSON query expressions using SQLite
Home-page: https://github.com/klahnakoski/jx-sqlite
Author: Rohit Kumar, Kyle Lahnakoski
Author-email: rohitkumar.a255@gmail.com, kyle@lahnakoski.com
License: MPL 2.0
Classifier: Development Status :: 3 - Alpha
Classifier: Topic :: Software Development :: Libraries
Classifier: Topic :: Software Development :: Libraries :: Python Modules
Classifier: License :: OSI Approved :: Mozilla Public License 2.0 (MPL 2.0)
Classifier: Topic :: Database
Classifier: Topic :: Utilities
Classifier: Programming Language :: SQL
Classifier: Programming Language :: Python :: 3.8
Classifier: Programming Language :: Python :: 3.9
Classifier: Programming Language :: Python :: 3.10
Classifier: Programming Language :: Python :: 3.11
Classifier: Programming Language :: Python :: 3.12
Classifier: Programming Language :: Python :: 3.13
License-File: LICENSE
Requires-Dist: hjson
Requires-Dist: jx-python==4.673.25037
Requires-Dist: mo-sql==4.672.25036
Requires-Dist: mo-sqlite==2.673.25037
Requires-Dist: requests
Provides-Extra: tests
Requires-Dist: mo-testing>=8.623.24125; extra == "tests"
Dynamic: author
Dynamic: author-email
Dynamic: classifier
Dynamic: description
Dynamic: description-content-type
Dynamic: home-page
Dynamic: license
Dynamic: provides-extra
Dynamic: requires-dist
Dynamic: summary
